Metadata-Version: 1.2
Name: python-pytuntap
Version: 1.0.0
Summary: Linux/Windows TUN/TAP wrapper for Python
Home-page: https://github.com/gonewind73/pytuntap
Author: gonewind.he
Author-email: gonewind.he@gmail.com
Maintainer: gonewind
Maintainer-email: gonewind.he@gmail.com
License: UNKNOWN
Platform: Linux
Platform: Windows
Classifier: Development Status :: 5 - Production/Stable
Classifier: Intended Audience :: Developers
Classifier: License :: OSI Approved :: MIT License
Classifier: Programming Language :: Python :: 3
Classifier: Topic :: Software Development :: Libraries :: Python Modules
Classifier: Topic :: System :: Networking
Requires-Python: >=3
